hat/controller/__init__.py
hat/controller/interpreters/quickjs.py
hat/controller/interpreters/_lua.abi3.pyd
hat/controller/environment.py
hat/controller/evaluators/common.py
hat/controller/interpreters/common.py
hat/controller/interpreters/lua.py
hat/controller/interpreters/_quickjs.abi3.pyd
hat/controller/interpreters/__init__.py
hat/controller/__main__.py
hat/controller/units/__init__.py
hat/controller/units/triggers.py
hat/controller/units/log.py
hat/controller/evaluators/lua.py
hat/controller/evaluators/py.py
hat/controller/runner.py
hat/controller/evaluators/js.py
hat/controller/engine.py
hat/controller/units/os.py
hat/controller/json_schema_repo.json
hat/controller/interpreters/duktape.py
hat/controller/units/timers.py
hat/controller/main.py
hat/controller/evaluators/__init__.py
hat/controller/common.py
hat/controller/interpreters/cpython.py
hat/controller/interpreters/_duktape.abi3.pyd
hat_controller-0.1.16.dist-info/LICENSE
hat_controller-0.1.16.dist-info/entry_points.txt
hat_controller-0.1.16.dist-info/METADATA
hat_controller-0.1.16.dist-info/WHEEL
hat_controller-0.1.16.dist-info/RECORD
