Metadata-Version: 2.1
Name: hat-controller
Version: 0.1.16
Summary: Hat controller
License: Apache-2.0
Provides-Extra: dev
Requires-Dist: appdirs ~=1.4.4
Requires-Dist: hat-aio ~=0.7.12
Requires-Dist: hat-json ~=0.6.3
Requires-Dist: hat-util ~=0.6.20
Requires-Dist: hat-doit ~=0.16.2; extra == 'dev'
Requires-Dist: peru >=1.3.1; extra == 'dev'
Requires-Dist: sphinxcontrib-programoutput >=0.17; extra == 'dev'
Requires-Python: >=3.10
Project-URL: Homepage, http://hat-open.com
Project-URL: Repository, https://github.com/hat-open/hat-controller.git
Project-URL: Documentation, http://hat-controller.hat-open.com
